HISTORY.rst
LICENSE
MANIFEST.in
README.rst
setup.cfg
setup.py
fuckitdb/__init__.py
fuckitdb/fuckit.py
fuckitdb.egg-info/PKG-INFO
fuckitdb.egg-info/SOURCES.txt
fuckitdb.egg-info/dependency_links.txt
fuckitdb.egg-info/not-zip-safe
fuckitdb.egg-info/requires.txt
fuckitdb.egg-info/top_level.txt