Metadata-Version: 1.1
Name: fuckitdb
Version: 0.1.3
Summary: fuckitdb is a Python ORM for Google Drive Spreadsheets.
Home-page: https://github.com/Widdershin/fuckitdb
Author: Nick Johnstone
Author-email: ncwjohnstone@gmail.com
License: MIT
Keywords: fuckitdb
Platform: UNKNOWN
Classifier: Development Status :: 2 - Pre-Alpha
Classifier: Intended Audience :: Developers
Classifier: Natural Language :: English
Classifier: Programming Language :: Python :: 2
Classifier: Programming Language :: Python :: 2.6
Classifier: Programming Language :: Python :: 2.7
